sanic_pika/__init__.py
sanic_pika/core.py
sanic_pika-0.1.0.dist-info/METADATA
sanic_pika-0.1.0.dist-info/WHEEL
sanic_pika-0.1.0.dist-info/top_level.txt
sanic_pika-0.1.0.dist-info/RECORD
